MANIFEST.in
README.rst
check_ganglia_metric.py
distribute_setup.py
setup.py
check_ganglia_metric.egg-info/PKG-INFO
check_ganglia_metric.egg-info/SOURCES.txt
check_ganglia_metric.egg-info/dependency_links.txt
check_ganglia_metric.egg-info/requires.txt
check_ganglia_metric.egg-info/top_level.txt