Metadata-Version: 1.0
Name: check-ganglia-metric
Version: 2012.02.28
Summary: Ganglia metric check plugin for Nagios
Home-page: http://github.com/mconigliaro/check_ganglia_metric
Author: Michael Paul Thomas Conigliaro
Author-email: mike [at] conigliaro [dot] org
License: UNKNOWN
Keywords: nagios ganglia monitoring
Platform: UNKNOWN
Classifier: Development Status :: 5 - Production/Stable
Classifier: Environment :: Console
Classifier: Intended Audience :: Information Technology
Classifier: Intended Audience :: System Administrators
Classifier: License :: Freely Distributable
Classifier: Natural Language :: English
Classifier: Operating System :: POSIX :: Linux
Classifier: Programming Language :: Python :: 2.6
Classifier: Topic :: System :: Monitoring
